m_parse/__init__.py
m_parse/main.py
m_parse/parse_json.py
m_parse/version.py
m_parse-0.1.9.dist-info/METADATA
m_parse-0.1.9.dist-info/WHEEL
m_parse-0.1.9.dist-info/entry_points.txt
m_parse-0.1.9.dist-info/top_level.txt
m_parse-0.1.9.dist-info/RECORD
