Metadata-Version: 2.1
Name: m-parse
Version: 0.1.9
Summary: 该工具用于解析json,输出csv,excel格式的数据
Home-page: UNKNOWN
Author: miaoxin
Author-email: miaorulai@gmail.com
License: MIT
Platform: UNKNOWN
Requires-Dist: argparse
Requires-Dist: xlwt
